nmfu.py
nmfu-0.5.7.dist-info/LICENSE
nmfu-0.5.7.dist-info/METADATA
nmfu-0.5.7.dist-info/WHEEL
nmfu-0.5.7.dist-info/entry_points.txt
nmfu-0.5.7.dist-info/top_level.txt
nmfu-0.5.7.dist-info/RECORD
