Metadata-Version: 2.1
Name: nmfu
Version: 0.5.7
Summary: A parser generator that turns procedural programs into C state machines
Home-page: https://github.com/mincrmatt12/nmfu
Author: Matthew Mirvish
Author-email: matthew@mm12.xyz
License: GPLv3
Project-URL: Bug Tracker, https://github.com/mincrmatt12/nmfu/issues
Project-URL: Source Code, https://github.com/mincrmatt12/nmfu
Keywords: c parser parser-generator cli tool
Classifier: Development Status :: 3 - Alpha
Classifier: Environment :: Console
Classifier: License :: OSI Approved :: GNU General Public License v3 (GPLv3)
Classifier: Intended Audience :: Developers
Classifier: Programming Language :: C
Classifier: Programming Language :: Python :: 3
Classifier: Programming Language :: Python :: 3.6
Classifier: Programming Language :: Python :: 3.7
Classifier: Programming Language :: Python :: 3.8
Classifier: Programming Language :: Python :: 3.9
Classifier: Topic :: Software Development :: Code Generators
Requires-Python: ~=3.6
License-File: LICENSE
Requires-Dist: lark>=1.0
Provides-Extra: coverage
Requires-Dist: pytest-cov; extra == "coverage"
Provides-Extra: debug
Requires-Dist: graphviz>=0.14; extra == "debug"
Provides-Extra: tests
Requires-Dist: pytest; extra == "tests"
Requires-Dist: hypothesis; extra == "tests"
